picta_dl/YoutubeDL.py
picta_dl/__init__.py
picta_dl/__main__.py
picta_dl/aes.py
picta_dl/cache.py
picta_dl/cookies.py
picta_dl/dependencies.py
picta_dl/jsinterp.py
picta_dl/minicurses.py
picta_dl/options.py
picta_dl/socks.py
picta_dl/update.py
picta_dl/utils.py
picta_dl/version.py
picta_dl/webvtt.py
picta_dl/compat/__init__.py
picta_dl/compat/_deprecated.py
picta_dl/compat/_legacy.py
picta_dl/compat/compat_utils.py
picta_dl/compat/functools.py
picta_dl/compat/imghdr.py
picta_dl/compat/shutil.py
picta_dl/downloader/__init__.py
picta_dl/downloader/common.py
picta_dl/downloader/dash.py
picta_dl/downloader/external.py
picta_dl/downloader/f4m.py
picta_dl/downloader/fc2.py
picta_dl/downloader/fragment.py
picta_dl/downloader/hls.py
picta_dl/downloader/http.py
picta_dl/downloader/ism.py
picta_dl/downloader/mhtml.py
picta_dl/downloader/niconico.py
picta_dl/downloader/rtmp.py
picta_dl/downloader/rtsp.py
picta_dl/downloader/websocket.py
picta_dl/downloader/youtube_live_chat.py
picta_dl/extractor/__init__.py
picta_dl/extractor/_extractors.py
picta_dl/extractor/adobepass.py
picta_dl/extractor/common.py
picta_dl/extractor/commonprotocols.py
picta_dl/extractor/extractors.py
picta_dl/extractor/facebook.py
picta_dl/extractor/generic.py
picta_dl/extractor/openload.py
picta_dl/extractor/picta.py
picta_dl/extractor/youtube.py
picta_dl/postprocessor/__init__.py
picta_dl/postprocessor/common.py
picta_dl/postprocessor/embedthumbnail.py
picta_dl/postprocessor/exec.py
picta_dl/postprocessor/ffmpeg.py
picta_dl/postprocessor/metadataparser.py
picta_dl/postprocessor/modify_chapters.py
picta_dl/postprocessor/movefilesafterdownload.py
picta_dl/postprocessor/sponskrub.py
picta_dl/postprocessor/sponsorblock.py
picta_dl/postprocessor/xattrpp.py
picta_dl-2022.11.30.data/data/etc/bash_completion.d/picta-dl.bash-completion
picta_dl-2022.11.30.data/data/etc/fish/completions/picta-dl.fish
picta_dl-2022.11.30.data/data/share/doc/picta_dl/README.txt
picta_dl-2022.11.30.data/data/share/man/man1/picta-dl.1
picta_dl-2022.11.30.dist-info/AUTHORS
picta_dl-2022.11.30.dist-info/LICENSE
picta_dl-2022.11.30.dist-info/METADATA
picta_dl-2022.11.30.dist-info/WHEEL
picta_dl-2022.11.30.dist-info/entry_points.txt
picta_dl-2022.11.30.dist-info/top_level.txt
picta_dl-2022.11.30.dist-info/RECORD
